pruna_launch_party/__init__.py
pruna_launch_party/cli.py
pruna_launch_party-1.0.0.dist-info/LICENSE
pruna_launch_party-1.0.0.dist-info/METADATA
pruna_launch_party-1.0.0.dist-info/WHEEL
pruna_launch_party-1.0.0.dist-info/entry_points.txt
pruna_launch_party-1.0.0.dist-info/top_level.txt
pruna_launch_party-1.0.0.dist-info/RECORD
