Metadata-Version: 2.2
Name: pruna-launch-party
Version: 1.0.0
Summary: A fun package celebrating Pruna's open-source launch!
Home-page: https://github.com/pruna-ai/pruna
Author: Pruna Team
Author-email: team@pruna.dev
Classifier: Development Status :: 4 - Beta
Classifier: Intended Audience :: Developers
Classifier: License :: OSI Approved :: MIT License
Classifier: Programming Language :: Python :: 3
Classifier: Programming Language :: Python :: 3.7
Classifier: Programming Language :: Python :: 3.8
Classifier: Programming Language :: Python :: 3.9
Classifier: Programming Language :: Python :: 3.10
Requires-Python: >=3.7
License-File: LICENSE
Requires-Dist: colorama>=0.4.6
Requires-Dist: tqdm>=4.65.0
Dynamic: author
Dynamic: author-email
Dynamic: classifier
Dynamic: description
Dynamic: description-content-type
Dynamic: home-page
Dynamic: requires-dist
Dynamic: requires-python
Dynamic: summary
